{
  "run_name": "exam62_20251231-143448",
  "image_name": "exam62.png",
  "results": [
    {
      "line_id": 0,
      "bbox": [
        164,
        55,
        662,
        90
      ],
      "paddle_text": "HANDWRITTEN EXAM SHEET (OCR EVALUATION)",
      "trocr_text": {
        "base": "HANDWRITTEN EXAM SHEET (OCR EVALUATION)",
        "large": "HANDWRITTEN EXAM SHEET (OCR EVALUATION)"
      },
      "easyocr": [
        "HANDWRITTEN",
        "EXAM SHEET (OCR EVALUATION)"
      ]
    },
    {
      "line_id": 1,
      "bbox": [
        107,
        89,
        484,
        120
      ],
      "paddle_text": "Section A — Numeric & Symbolic Answers",
      "trocr_text": {
        "base": "SECTION A - NUMERIC & SYMBOLIC ANSWERS",
        "large": "SECTION A - NUMERIC & SYMBOLIC ANSWERS"
      },
      "easyocr": [
        "Section",
        "Numeric",
        "Symbolic",
        "Answers"
      ]
    },
    {
      "line_id": 2,
      "bbox": [
        107,
        116,
        218,
        137
      ],
      "paddle_text": "130-10=20",
      "trocr_text": {
        "base": "1) 30 -10 = 2 0",
        "large": "1) 30 - 10 = 20"
      },
      "easyocr": [
        "1) 30"
      ]
    },
    {
      "line_id": 3,
      "bbox": [
        103,
        136,
        202,
        160
      ],
      "paddle_text": "2)7×8=56",
      "trocr_text": {
        "base": "2)7X8= 56",
        "large": "2) 7 X 8 = 56"
      },
      "easyocr": [
        "2) 7 * 8",
        "56"
      ]
    },
    {
      "line_id": 4,
      "bbox": [
        103,
        157,
        203,
        182
      ],
      "paddle_text": "396÷6=16",
      "trocr_text": {
        "base": "3) 96 + 6 = / 6",
        "large": "3) 96 - 6 = 16"
      },
      "easyocr": [
        "3) 96"
      ]
    },
    {
      "line_id": 5,
      "bbox": [
        103,
        180,
        228,
        203
      ],
      "paddle_text": "4-18+11=-7",
      "trocr_text": {
        "base": "4)-18+11 = - 7",
        "large": "4)-18+11 = - 7"
      },
      "easyocr": []
    },
    {
      "line_id": 6,
      "bbox": [
        101,
        200,
        216,
        226
      ],
      "paddle_text": "5)2.4+3=5.4",
      "trocr_text": {
        "base": "5) 24+3= 5.24",
        "large": "5) 2.4 + 3 = 5.4"
      },
      "easyocr": [
        "5) 24+3"
      ]
    },
    {
      "line_id": 7,
      "bbox": [
        101,
        222,
        214,
        247
      ],
      "paddle_text": "692-47=45",
      "trocr_text": {
        "base": "6) 92 - 47 = 4 5",
        "large": "6) 92 - 47 = 4 5"
      },
      "easyocr": [
        "47 =",
        "45"
      ]
    },
    {
      "line_id": 8,
      "bbox": [
        100,
        244,
        184,
        268
      ],
      "paddle_text": "7) $3^3=27",
      "trocr_text": {
        "base": "7)33 = 27",
        "large": "7)33 - 27"
      },
      "easyocr": [
        "7) 3\"",
        "27"
      ]
    },
    {
      "line_id": 9,
      "bbox": [
        100,
        268,
        212,
        289
      ],
      "paddle_text": "8150÷5=30",
      "trocr_text": {
        "base": "8) 150 +5= 30",
        "large": "8) 150 + 5 = 30"
      },
      "easyocr": [
        "8) 150",
        "5 -"
      ]
    },
    {
      "line_id": 10,
      "bbox": [
        99,
        290,
        203,
        312
      ],
      "paddle_text": "38-19=19",
      "trocr_text": {
        "base": "9) 38-19=19",
        "large": "9) 38 - 19 = / 91"
      },
      "easyocr": [
        "9) 38",
        "19"
      ]
    },
    {
      "line_id": 11,
      "bbox": [
        95,
        308,
        205,
        336
      ],
      "paddle_text": "10)9×9=81",
      "trocr_text": {
        "base": "10) 9 X 9 = 8 1",
        "large": "10)9X9=81"
      },
      "easyocr": [
        "10) 9 x 9"
      ]
    },
    {
      "line_id": 12,
      "bbox": [
        93,
        379,
        408,
        411
      ],
      "paddle_text": "Section B — Single Word Answers",
      "trocr_text": {
        "base": "SECTION B - SINGLE WORLD ANSWERS",
        "large": "SECTION B - SINGLE WORD ANSWERS"
      },
      "easyocr": [
        "Section B",
        "Single Word",
        "Answers"
      ]
    },
    {
      "line_id": 13,
      "bbox": [
        93,
        416,
        379,
        441
      ],
      "paddle_text": "11) Opposite of \"minimum\": maximum",
      "trocr_text": {
        "base": "11) OPPOSITE OF \"MINIMUM\":_MAXINJUN",
        "large": "11) OPPOSITE OF \"MINIMUM\": MAXIMUM"
      },
      "easyocr": [
        "11) Opposite",
        "minimum",
        "mazimum"
      ]
    },
    {
      "line_id": 14,
      "bbox": [
        91,
        444,
        424,
        475
      ],
      "paddle_text": "12) Word meaning \"not allowed\": orbidden",
      "trocr_text": {
        "base": "12) WORLD MEANING \"NOT ALLOWED\": PERBIDEDEN",
        "large": "12) WORD MEANING \"NOT ALLOWED\": PERBIDEDEN"
      },
      "easyocr": [
        "12) Word meaning",
        "allowed",
        "fecbAd",
        "cnot"
      ]
    },
    {
      "line_id": 15,
      "bbox": [
        91,
        482,
        452,
        506
      ],
      "paddle_text": "13) Color formed by mixing blue and yellow: goee",
      "trocr_text": {
        "base": "13) COLOR FORMED BY MIXING BLUE AND YELLOW: _9REEA",
        "large": "13) COLOR FORMED BY MIXING BLUE AND YELLOW: GREEN"
      },
      "easyocr": [
        "13) Color formed by mixing blue and yellow:",
        "gceea"
      ]
    },
    {
      "line_id": 16,
      "bbox": [
        89,
        510,
        362,
        539
      ],
      "paddle_text": "1) Plural of \"analysis\": anclyse",
      "trocr_text": {
        "base": "14) PLURAL OF \"ANALYSIS\": _GINGLASE 5",
        "large": "14) PLURAL OF \"ANALYSIS\": ANGLYSES"
      },
      "easyocr": [
        "14) Plural of \"analysis\"",
        "Anc",
        "39"
      ]
    },
    {
      "line_id": 17,
      "bbox": [
        86,
        541,
        427,
        571
      ],
      "paddle_text": "1 Animal with black and white stripes:bc",
      "trocr_text": {
        "base": "15) ANIMAL WITH BLACK AND WHITE STRIPES: ZELBACA",
        "large": "15) ANIMAL WITH BLACK AND WHITE STRIPES: ZEBRA"
      },
      "easyocr": [
        "15)",
        "Animal with black and white stripes:",
        "2e504"
      ]
    },
    {
      "line_id": 18,
      "bbox": [
        85,
        574,
        352,
        603
      ],
      "paddle_text": "1) Past tense of \"write\": Wrot",
      "trocr_text": {
        "base": "16) PAST TENSE OF \"WRITE\": _UVROLE",
        "large": "16) PAST TENSE OF \"WRITE\" : _ WROTE"
      },
      "easyocr": [
        "16) Past tense of \"write\"",
        "Wno4"
      ]
    },
    {
      "line_id": 19,
      "bbox": [
        85,
        672,
        414,
        692
      ],
      "paddle_text": "Section C -Short Phrase Answers",
      "trocr_text": {
        "base": "SECTION C - SHORT PHASE ANSWERS",
        "large": "SECTION C - SHORT PHRASE ANSWERS"
      },
      "easyocr": [
        "Section",
        "Short Phrase Answers"
      ]
    },
    {
      "line_id": 20,
      "bbox": [
        84,
        695,
        249,
        714
      ],
      "paddle_text": "(Write 2-3 words exactly)",
      "trocr_text": {
        "base": "(WRITE 2-3 WORDS EXACTLY)",
        "large": "(WRITE 2-3 WORDS EXACTLY)"
      },
      "easyocr": [
        "(Write 2-8 words eractl"
      ]
    },
    {
      "line_id": 21,
      "bbox": [
        81,
        718,
        370,
        742
      ],
      "paddle_text": "17Technology for reading text from images:",
      "trocr_text": {
        "base": "17) TECHNOLOGY FOR READING TEXT FROM IMAGES:",
        "large": "17) TECHNOLOGY FOR READING TEXT FROM IMAGES:"
      },
      "easyocr": [
        "17) Technology for reading text from irages"
      ]
    },
    {
      "line_id": 22,
      "bbox": [
        104,
        727,
        440,
        772
      ],
      "paddle_text": "optical character recognition",
      "trocr_text": {
        "base": "OPTICAL CHARCETAR RECOGRITION",
        "large": "OPTICAL CHARGETER RECOGRITION"
      },
      "easyocr": [
        "Oplical",
        "cherecten",
        "e@oq",
        "nilion"
      ]
    },
    {
      "line_id": 23,
      "bbox": [
        80,
        770,
        358,
        790
      ],
      "paddle_text": "18) Field that combines data and statistics:",
      "trocr_text": {
        "base": "18) FIELD THAT COMBINES DATE AND STATISTICS:",
        "large": "18) FIELD THAT COMBINES DATE AND STATISTICS:"
      },
      "easyocr": [
        "18)",
        "Field that combines data and statistics:"
      ]
    },
    {
      "line_id": 24,
      "bbox": [
        108,
        789,
        266,
        818
      ],
      "paddle_text": "data science",
      "trocr_text": {
        "base": "JATE SCIENCE",
        "large": "DATE SCIENCE"
      },
      "easyocr": [
        "dala",
        "sciene"
      ]
    },
    {
      "line_id": 25,
      "bbox": [
        77,
        821,
        318,
        841
      ],
      "paddle_text": "19) Portable computer used for work:",
      "trocr_text": {
        "base": "19) PORTABLE COMPUTER USED FOR WORK:",
        "large": "19) PORTABLE COMPUTER USED FOR WORK:"
      },
      "easyocr": [
        "19) Portable computer used for work:"
      ]
    },
    {
      "line_id": 26,
      "bbox": [
        111,
        841,
        295,
        871
      ],
      "paddle_text": "laptop computer",
      "trocr_text": {
        "base": "LAPTOP COMPULAR",
        "large": "LAPTOP COMPUTER"
      },
      "easyocr": [
        "laplop campter"
      ]
    },
    {
      "line_id": 27,
      "bbox": [
        74,
        870,
        350,
        894
      ],
      "paddle_text": "20) Method used to train neural networks:",
      "trocr_text": {
        "base": "20) METHOD USED TO TRAIN NEURAL NETWORK:",
        "large": "20) METHOD USED TO TRAIN NEURAL NETWORKS:"
      },
      "easyocr": [
        "20) Method used to train neural networks:"
      ]
    },
    {
      "line_id": 28,
      "bbox": [
        106,
        892,
        313,
        930
      ],
      "paddle_text": "backpropagation",
      "trocr_text": {
        "base": "BACKPROPAGATION",
        "large": "BACKPROPOGRATION"
      },
      "easyocr": [
        "backeropostion"
      ]
    }
  ]
}